let_me_google_that_for_you/let_me_google_that_for_you/main.py
let_me_google_that_for_you/README.rst
let_me_google_that_for_you-0.0.3.dist-info/WHEEL
let_me_google_that_for_you-0.0.3.dist-info/METADATA
let_me_google_that_for_you-0.0.3.dist-info/RECORD
