Metadata-Version: 2.1
Name: let-me-google-that-for-you
Version: 0.0.3
Summary: Paclage
License: n
Author: Your Name
Author-email: you@example.com
Requires-Python: >=3.5,<4.0
Classifier: License :: Other/Proprietary License
Classifier: Programming Language :: Python :: 3
Classifier: Programming Language :: Python :: 3.10
Classifier: Programming Language :: Python :: 3.5
Classifier: Programming Language :: Python :: 3.6
Classifier: Programming Language :: Python :: 3.7
Classifier: Programming Language :: Python :: 3.8
Classifier: Programming Language :: Python :: 3.9
